tenneteu/__init__.py
tenneteu/exceptions.py
tenneteu/tenneteu.py
tenneteu_py-0.1.4.dist-info/licenses/LICENSE.MD
tenneteu_py-0.1.4.dist-info/METADATA
tenneteu_py-0.1.4.dist-info/WHEEL
tenneteu_py-0.1.4.dist-info/top_level.txt
tenneteu_py-0.1.4.dist-info/RECORD
