Metadata-Version: 2.4
Name: tenneteu-py
Version: 0.1.4
Summary: A python API wrapper for tennet.eu API
Home-page: https://github.com/fboerman/TenneTeu-py
Author: Frank Boerman
Author-email: frank@fboerman.nl
License: MIT
Keywords: TenneT data api energy
Classifier: Development Status :: 4 - Beta
Classifier: Intended Audience :: Developers
Classifier: Topic :: Scientific/Engineering
Classifier: License :: OSI Approved :: MIT License
Classifier: Programming Language :: Python :: 3.9
Classifier: Programming Language :: Python :: 3.10
Classifier: Programming Language :: Python :: 3.11
License-File: LICENSE.MD
Requires-Dist: requests
Requires-Dist: pandas
Dynamic: author
Dynamic: author-email
Dynamic: classifier
Dynamic: description
Dynamic: description-content-type
Dynamic: home-page
Dynamic: keywords
Dynamic: license
Dynamic: license-file
Dynamic: requires-dist
Dynamic: summary
